Iguape/Monitor.py
Iguape/__init__.py
Iguape/iguape.py
Iguape/launcher.py
Iguape/GUI/__init__.py
Iguape/GUI/export_figure.py
Iguape/GUI/export_figure.ui
Iguape/GUI/filter_gui.py
Iguape/GUI/filter_gui.ui
Iguape/GUI/iguape_GUI.py
Iguape/GUI/iguape_gui.ui
Iguape/GUI/pk_window.py
Iguape/GUI/pk_window.ui
Iguape/Icons/CNPEM-logo-colorido-2023_resize.png
Iguape/Icons/Filter_Icon.png
Iguape/Icons/LNLS_logo_resize.png
Iguape/Icons/Logo_IGUAPE.ico
Iguape/Icons/Logo_IGUAPE.png
Iguape/Icons/Logo_IGUAPE_resized.png
Iguape/Icons/Paineira_resize.png
Iguape/Icons/Refresh_Icon.png
Iguape/Icons/Save_Icon.png
Iguape/Icons/Splash_Screen.jpg
Iguape/Icons/peak_fit_icon.png
Iguape/Icons/temperature_icon.png
iguape-1.2.6.dist-info/licenses/LICENSE.txt
iguape-1.2.6.dist-info/METADATA
iguape-1.2.6.dist-info/WHEEL
iguape-1.2.6.dist-info/entry_points.txt
iguape-1.2.6.dist-info/top_level.txt
iguape-1.2.6.dist-info/RECORD
