Metadata-Version: 2.4
Name: iguape
Version: 1.2.6
Summary: Iguape is a Graphical User Interface for X-ray diffraction in situ experiments at Paineira beamline (LNLS/CNPEM).
Author: Junior Cintra Mauricio, Cristiane Barbieri Rodella
Author-email: João Luis Biondo Neto <joaoluisbiondo@gmail.com>
Maintainer-email: João Luis Biondo Neto <joaoluisbiondo@gmail.com>
License:                     GNU GENERAL PUBLIC LICENSE
Project-URL: Repository, https://github.com/cnpem/Iguape
Keywords: X-ray diffraction,in situ experiments,XRD synchrotron
Classifier: Development Status :: 4 - Beta
Classifier: Programming Language :: Python
Classifier: License :: OSI Approved :: GNU General Public License v3 (GPLv3)
Classifier: Operating System :: OS Independent
Classifier: Intended Audience :: Science/Research
Classifier: Topic :: Scientific/Engineering :: Physics
Classifier: Topic :: Scientific/Engineering :: Chemistry
Requires-Python: >=3.10
License-File: LICENSE.txt
Requires-Dist: PyQt5==5.15.10
Requires-Dist: numpy==1.26.4
Requires-Dist: pandas==2.2.2
Requires-Dist: scipy==1.13.1
Requires-Dist: matplotlib==3.8.4
Requires-Dist: lmfit==1.3.1
Dynamic: license-file
